Workbook

Sheet Mode d'emploi
A1: SoA – ISO/IEC 27001:2022 – Orséa Banque
A2: Déclaration d'applicabilité des 93 contrôles de l'Annexe A, issue de l'analyse de risques EBIOS RM (AR_01).
A4: Comment reporter dans CISO Assistant (audit AUD_01, annex-a) :
A5: 1. Result : recopier la colonne « Résultat CISO » (Not applicable / Non compliant / Partially compliant).
A6: 2. Status : mettre « Done » une fois la ligne évaluée.
A7: 3. Applied control : ajouter les mesures de la colonne « Mesures Orséa » (rechercher par nom).
A8: 4. Observation : coller la colonne « Justification ».
A10: Règle d'évaluation (état initial, avant mise en œuvre du plan de traitement) :
A11: • Not applicable : contrôle exclu, avec justification obligatoire (clause 6.1.3 d).
A12: • Partially compliant : une mesure ou un livrable existe déjà (M_01 active, inventaire et DICP de l'atelier 1, cadre de suivi).
A13: • Non compliant : mesure prévue (statut « To do ») ou à couvrir par la PSSI.
A15: Cellules modifiables : colonnes D (Applicable) et H (Résultat) de l'onglet SoA. Le tableau de synthèse se met à jour automatiquement.

Sheet SoA
A1: Réf. | B1: Thème | C1: Contrôle (Annexe A) | D1: Applicable | E1: Justification | F1: Mesures Orséa | G1: Risques couverts | H1: Résultat CISO
A2: 5.1 | B2: 5 – Organisationnel | C2: Politiques de sécurité de l'information | D2: Oui | E2: Socle obligatoire du SMSI ; exigé par DORA (art. 5-6) pour le cadre de gestion du risque TIC. | F2: PSSI (à rédiger) | G2: Tous | H2: Non compliant
A3: 5.2 | B3: 5 – Organisationnel | C3: Fonctions et responsabilités liées à la sécurité | D3: Oui | E3: Le RSSI est propriétaire du cadre de suivi des risques ; les rôles doivent être formalisés. | F3: Cadre de suivi AR_01 | G3: Tous | H3: Partially compliant
A4: 5.3 | B4: 5 – Organisationnel | C4: Séparation des tâches | D4: Oui | E4: Un agent seul ne doit pas pouvoir valider une opération sensible (fraude interne). | F4: M_22 | G4: CA_05 | H4: Non compliant
A5: 5.4 | B5: 5 – Organisationnel | C5: Responsabilités de la direction | D5: Oui | E5: DORA rend l'organe de direction responsable du risque TIC ; reporting COMEX prévu. | F5: Cadre de suivi AR_01 | G5: Tous | H5: Partially compliant
A6: 5.5 | B6: 5 – Organisationnel | C6: Contacts avec les autorités | D6: Oui | E6: Notification des incidents majeurs à l'ACPR (DORA), déclarations Tracfin, CNIL (RGPD). | F6: M_16, M_19 | G6: CA_01 à CA_07 | H6: Non compliant
A7: 5.6 | B7: 5 – Organisationnel | C7: Contacts avec des groupes d'intérêt spéciaux | D7: Oui | E7: Partage d'information sur les menaces avec CERT-FR et la communauté bancaire. | F7: PSSI (à rédiger) | G7: CA_01, CA_03 | H7: Non compliant
A8: 5.7 | B8: 5 – Organisationnel | C8: Renseignement sur les menaces | D8: Oui | E8: Les menaces (phishing, rançongiciel) évoluent vite ; veille assurée par le SOC. | F8: M_14 | G8: CA_01, CA_03, CA_04 | H8: Non compliant
A9: 5.8 | B9: 5 – Organisationnel | C9: Sécurité de l'information dans la gestion de projet | D9: Oui | E9: Les évolutions de l'appli et du core banking doivent intégrer la sécurité dès la conception. | F9: PSSI (à rédiger) | G9: CA_04 | H9: Non compliant
A10: 5.9 | B10: 5 – Organisationnel | C10: Inventaire des informations et autres actifs associés | D10: Oui | E10: Valeurs métier et biens supports inventoriés lors de l'atelier 1 EBIOS RM. | F10: Atelier 1 EBIOS RM | G10: Tous | H10: Partially compliant
A11: 5.10 | B11: 5 – Organisationnel | C11: Utilisation correcte des informations et actifs | D11: Oui | E11: Charte d'utilisation des SI à faire signer aux collaborateurs. | F11: PSSI (à rédiger) | G11: CA_03, CA_05 | H11: Non compliant
A12: 5.11 | B12: 5 – Organisationnel | C12: Restitution des actifs | D12: Oui | E12: Restitution du matériel et des accès au départ d'un collaborateur. | F12: M_22 | G12: CA_05 | H12: Non compliant
... A94: 8.34 | B94: 8 – Technologique | C94: Protection des SI en cours d'audit | D94: Oui | E94: Encadrer les audits et tests TLPT pour ne pas perturber la production. | F94: PSSI (à rédiger) | G94: — | H94: Non compliant

Sheet Synthèse
A1: Thème | B1: Contrôles | C1: Applicables | D1: Exclus | E1: Partially compliant | F1: Non compliant | G1: Taux d'applicabilité
A2: 5 – Organisationnel | B2: =COUNTIF(SoA!$B$2:$B$94,A2) -> 37 | C2: =COUNTIFS(SoA!$B$2:$B$94,A2,SoA!$D$2:$D$94,"Oui") -> 37 | D2: =COUNTIFS(SoA!$B$2:$B$94,A2,SoA!$D$2:$D$94,"Non") -> 0 | E2: =COUNTIFS(SoA!$B$2:$B$94,A2,SoA!$H$2:$H$94,"Partially compliant") -> 5 | F2: =COUNTIFS(SoA!$B$2:$B$94,A2,SoA!$H$2:$H$94,"Non compliant") -> 32 | G2: =IFERROR(C2/B2,0) -> 1
A3: 6 – Personnes | B3: =COUNTIF(SoA!$B$2:$B$94,A3) -> 8 | C3: =COUNTIFS(SoA!$B$2:$B$94,A3,SoA!$D$2:$D$94,"Oui") -> 8 | D3: =COUNTIFS(SoA!$B$2:$B$94,A3,SoA!$D$2:$D$94,"Non") -> 0 | E3: =COUNTIFS(SoA!$B$2:$B$94,A3,SoA!$H$2:$H$94,"Partially compliant") -> 0 | F3: =COUNTIFS(SoA!$B$2:$B$94,A3,SoA!$H$2:$H$94,"Non compliant") -> 8 | G3: =IFERROR(C3/B3,0) -> 1
A4: 7 – Physique | B4: =COUNTIF(SoA!$B$2:$B$94,A4) -> 14 | C4: =COUNTIFS(SoA!$B$2:$B$94,A4,SoA!$D$2:$D$94,"Oui") -> 11 | D4: =COUNTIFS(SoA!$B$2:$B$94,A4,SoA!$D$2:$D$94,"Non") -> 3 | E4: =COUNTIFS(SoA!$B$2:$B$94,A4,SoA!$H$2:$H$94,"Partially compliant") -> 0 | F4: =COUNTIFS(SoA!$B$2:$B$94,A4,SoA!$H$2:$H$94,"Non compliant") -> 11 | G4: =IFERROR(C4/B4,0) -> 0.78571429
A5: 8 – Technologique | B5: =COUNTIF(SoA!$B$2:$B$94,A5) -> 34 | C5: =COUNTIFS(SoA!$B$2:$B$94,A5,SoA!$D$2:$D$94,"Oui") -> 34 | D5: =COUNTIFS(SoA!$B$2:$B$94,A5,SoA!$D$2:$D$94,"Non") -> 0 | E5: =COUNTIFS(SoA!$B$2:$B$94,A5,SoA!$H$2:$H$94,"Partially compliant") -> 1 | F5: =COUNTIFS(SoA!$B$2:$B$94,A5,SoA!$H$2:$H$94,"Non compliant") -> 33 | G5: =IFERROR(C5/B5,0) -> 1
A6: Total | B6: =SUM(B2:B5) -> 93 | C6: =SUM(C2:C5) -> 90 | D6: =SUM(D2:D5) -> 3 | E6: =SUM(E2:E5) -> 6 | F6: =SUM(F2:F5) -> 84 | G6: =IFERROR(C6/B6,0) -> 0.96774194
